{"count":56,"next":null,"previous":null,"results":[{"city":"Manaus","city_ibge_code":"1302603","confirmed":7264,"confirmed_per_100k_inhabitants":332.78922,"date":"2020-05-11","death_rate":0.0951,"deaths":691,"estimated_population_2019":2182763,"is_last":true,"order_for_place":56,"place_type":"city","state":"AM"},{"city":"Manaus","city_ibge_code":"1302603","confirmed":7198,"confirmed_per_100k_inhabitants":329.76553,"date":"2020-05-10","death_rate":0.0945,"deaths":680,"estimated_population_2019":2182763,"is_last":false,"order_for_place":55,"place_type":"city","state":"AM"},{"city":"Manaus","city_ibge_code":"1302603","confirmed":6743,"confirmed_per_100k_inhabitants":308.92039,"date":"2020-05-09","death_rate":0.0979,"deaths":660,"estimated_population_2019":2182763,"is_last":false,"order_for_place":54,"place_type":"city","state":"AM"},{"city":"Manaus","city_ibge_code":"1302603","confirmed":6034,"confirmed_per_100k_inhabitants":276.43862,"date":"2020-05-08","death_rate":0.1001,"deaths":604,"estimated_population_2019":2182763,"is_last":false,"order_for_place":53,"place_type":"city","state":"AM"},{"city":"Manaus","city_ibge_code":"1302603","confirmed":5897,"confirmed_per_100k_inhabitants":270.16218,"date":"2020-05-07","death_rate":0.0955,"deaths":563,"estimated_population_2019":2182763,"is_last":false,"order_for_place":52,"place_type":"city","state":"AM"},{"city":"Manaus","city_ibge_code":"1302603","confirmed":5474,"confirmed_per_100k_inhabitants":250.78307,"date":"2020-05-06","death_rate":0.0972,"deaths":532,"estimated_population_2019":2182763,"is_last":false,"order_for_place":51,"place_type":"city","state":"AM"},{"city":"Manaus","city_ibge_code":"1302603","confirmed":4804,"confirmed_per_100k_inhabitants":220.08803,"date":"2020-05-05","death_rate":0.0955,"deaths":459,"estimated_population_2019":2182763,"is_last":false,"order_for_place":50,"place_type":"city","state":"AM"},{"city":"Manaus","city_ibge_code":"1302603","confirmed":4344,"confirmed_per_100k_inhabitants":199.01382,"date":"2020-05-04","death_rate":0.0962,"deaths":418,"estimated_population_2019":2182763,"is_last":false,"order_for_place":49,"place_type":"city","state":"AM"},{"city":"Manaus","city_ibge_code":"1302603","confirmed":4072,"confirmed_per_100k_inhabitants":186.55255,"date":"2020-05-03","death_rate":0.0972,"deaths":396,"estimated_population_2019":2182763,"is_last":false,"order_for_place":48,"place_type":"city","state":"AM"},{"city":"Manaus","city_ibge_code":"1302603","confirmed":3658,"confirmed_per_100k_inhabitants":167.58576,"date":"2020-05-02","death_rate":0.1006,"deaths":368,"estimated_population_2019":2182763,"is_last":false,"order_for_place":47,"place_type":"city","state":"AM"},{"city":"Manaus","city_ibge_code":"1302603","confirmed":3491,"confirmed_per_100k_inhabitants":159.93491,"date":"2020-05-01","death_rate":0.1023,"deaths":357,"estimated_population_2019":2182763,"is_last":false,"order_for_place":46,"place_type":"city","state":"AM"},{"city":"Manaus","city_ibge_code":"1302603","confirmed":3273,"confirmed_per_100k_inhabitants":149.94757,"date":"2020-04-30","death_rate":0.0953,"deaths":312,"estimated_population_2019":2182763,"is_last":false,"order_for_place":45,"place_type":"city","state":"AM"},{"city":"Manaus","city_ibge_code":"1302603","confirmed":3091,"confirmed_per_100k_inhabitants":141.60951,"date":"2020-04-29","death_rate":0.0932,"deaths":288,"estimated_population_2019":2182763,"is_last":false,"order_for_place":44,"place_type":"city","state":"AM"},{"city":"Manaus","city_ibge_code":"1302603","confirmed":2899,"confirmed_per_100k_inhabitants":132.81332,"date":"2020-04-28","death_rate":0.0945,"deaths":274,"estimated_population_2019":2182763,"is_last":false,"order_for_place":43,"place_type":"city","state":"AM"},{"city":"Manaus","city_ibge_code":"1302603","confirmed":2738,"confirmed_per_100k_inhabitants":125.43735,"date":"2020-04-27","death_rate":0.0935,"deaths":256,"estimated_population_2019":2182763,"is_last":false,"order_for_place":42,"place_type":"city","state":"AM"},{"city":"Manaus","city_ibge_code":"1302603","confirmed":2722,"confirmed_per_100k_inhabitants":124.70433,"date":"2020-04-26","death_rate":0.0904,"deaths":246,"estimated_population_2019":2182763,"is_last":false,"order_for_place":41,"place_type":"city","state":"AM"},{"city":"Manaus","city_ibge_code":"1302603","confirmed":2678,"confirmed_per_100k_inhabitants":122.68854,"date":"2020-04-25","death_rate":0.087,"deaths":233,"estimated_population_2019":2182763,"is_last":false,"order_for_place":40,"place_type":"city","state":"AM"},{"city":"Manaus","city_ibge_code":"1302603","confirmed":2481,"confirmed_per_100k_inhabitants":113.66328,"date":"2020-04-24","death_rate":0.0834,"deaths":207,"estimated_population_2019":2182763,"is_last":false,"order_for_place":39,"place_type":"city","state":"AM"},{"city":"Manaus","city_ibge_code":"1302603","confirmed":2286,"confirmed_per_100k_inhabitants":104.72965,"date":"2020-04-23","death_rate":0.0844,"deaths":193,"estimated_population_2019":2182763,"is_last":false,"order_for_place":38,"place_type":"city","state":"AM"},{"city":"Manaus","city_ibge_code":"1302603","confirmed":1958,"confirmed_per_100k_inhabitants":89.70282,"date":"2020-04-22","death_rate":0.0878,"deaths":172,"estimated_population_2019":2182763,"is_last":false,"order_for_place":37,"place_type":"city","state":"AM"},{"city":"Manaus","city_ibge_code":"1302603","confirmed":1809,"confirmed_per_100k_inhabitants":82.87661,"date":"2020-04-21","death_rate":0.0901,"deaths":163,"estimated_population_2019":2182763,"is_last":false,"order_for_place":36,"place_type":"city","state":"AM"},{"city":"Manaus","city_ibge_code":"1302603","confirmed":1772,"confirmed_per_100k_inhabitants":81.18151,"date":"2020-04-20","death_rate":0.088,"deaths":156,"estimated_population_2019":2182763,"is_last":false,"order_for_place":35,"place_type":"city","state":"AM"},{"city":"Manaus","city_ibge_code":"1302603","confirmed":1664,"confirmed_per_100k_inhabitants":76.23365,"date":"2020-04-19","death_rate":0.0931,"deaths":155,"estimated_population_2019":2182763,"is_last":false,"order_for_place":34,"place_type":"city","state":"AM"},{"city":"Manaus","city_ibge_code":"1302603","confirmed":1593,"confirmed_per_100k_inhabitants":72.9809,"date":"2020-04-18","death_rate":0.0841,"deaths":134,"estimated_population_2019":2182763,"is_last":false,"order_for_place":33,"place_type":"city","state":"AM"},{"city":"Manaus","city_ibge_code":"1302603","confirmed":1531,"confirmed_per_100k_inhabitants":70.14046,"date":"2020-04-17","death_rate":0.083,"deaths":127,"estimated_population_2019":2182763,"is_last":false,"order_for_place":32,"place_type":"city","state":"AM"},{"city":"Manaus","city_ibge_code":"1302603","confirmed":1459,"confirmed_per_100k_inhabitants":66.84189,"date":"2020-04-16","death_rate":0.0733,"deaths":107,"estimated_population_2019":2182763,"is_last":false,"order_for_place":31,"place_type":"city","state":"AM"},{"city":"Manaus","city_ibge_code":"1302603","confirmed":1350,"confirmed_per_100k_inhabitants":61.84822,"date":"2020-04-15","death_rate":0.0681,"deaths":92,"estimated_population_2019":2182763,"is_last":false,"order_for_place":30,"place_type":"city","state":"AM"},{"city":"Manaus","city_ibge_code":"1302603","confirmed":1295,"confirmed_per_100k_inhabitants":59.32847,"date":"2020-04-14","death_rate":0.0625,"deaths":81,"estimated_population_2019":2182763,"is_last":false,"order_for_place":29,"place_type":"city","state":"AM"},{"city":"Manaus","city_ibge_code":"1302603","confirmed":1106,"confirmed_per_100k_inhabitants":50.66972,"date":"2020-04-13","death_rate":0.0542,"deaths":60,"estimated_population_2019":2182763,"is_last":false,"order_for_place":28,"place_type":"city","state":"AM"},{"city":"Manaus","city_ibge_code":"1302603","confirmed":1053,"confirmed_per_100k_inhabitants":48.24161,"date":"2020-04-12","death_rate":0.0484,"deaths":51,"estimated_population_2019":2182763,"is_last":false,"order_for_place":27,"place_type":"city","state":"AM"},{"city":"Manaus","city_ibge_code":"1302603","confirmed":932,"confirmed_per_100k_inhabitants":42.69818,"date":"2020-04-11","death_rate":0.0483,"deaths":45,"estimated_population_2019":2182763,"is_last":false,"order_for_place":26,"place_type":"city","state":"AM"},{"city":"Manaus","city_ibge_code":"1302603","confirmed":863,"confirmed_per_100k_inhabitants":39.53705,"date":"2020-04-10","death_rate":0.0487,"deaths":42,"estimated_population_2019":2182763,"is_last":false,"order_for_place":25,"place_type":"city","state":"AM"},{"city":"Manaus","city_ibge_code":"1302603","confirmed":800,"confirmed_per_100k_inhabitants":36.6508,"date":"2020-04-09","death_rate":0.0413,"deaths":33,"estimated_population_2019":2182763,"is_last":false,"order_for_place":24,"place_type":"city","state":"AM"},{"city":"Manaus","city_ibge_code":"1302603","confirmed":712,"confirmed_per_100k_inhabitants":32.61921,"date":"2020-04-08","death_rate":0.0351,"deaths":25,"estimated_population_2019":2182763,"is_last":false,"order_for_place":23,"place_type":"city","state":"AM"},{"city":"Manaus","city_ibge_code":"1302603","confirmed":560,"confirmed_per_100k_inhabitants":25.65556,"date":"2020-04-07","death_rate":0.0339,"deaths":19,"estimated_population_2019":2182763,"is_last":false,"order_for_place":22,"place_type":"city","state":"AM"},{"city":"Manaus","city_ibge_code":"1302603","confirmed":473,"confirmed_per_100k_inhabitants":21.66978,"date":"2020-04-06","death_rate":0.0317,"deaths":15,"estimated_population_2019":2182763,"is_last":false,"order_for_place":21,"place_type":"city","state":"AM"},{"city":"Manaus","city_ibge_code":"1302603","confirmed":379,"confirmed_per_100k_inhabitants":17.36331,"date":"2020-04-05","death_rate":0.029,"deaths":11,"estimated_population_2019":2182763,"is_last":false,"order_for_place":20,"place_type":"city","state":"AM"},{"city":"Manaus","city_ibge_code":"1302603","confirmed":283,"confirmed_per_100k_inhabitants":12.96522,"date":"2020-04-04","death_rate":0.0318,"deaths":9,"estimated_population_2019":2182763,"is_last":false,"order_for_place":19,"place_type":"city","state":"AM"},{"city":"Manaus","city_ibge_code":"1302603","confirmed":232,"confirmed_per_100k_inhabitants":10.62873,"date":"2020-04-03","death_rate":0.0216,"deaths":5,"estimated_population_2019":2182763,"is_last":false,"order_for_place":18,"place_type":"city","state":"AM"},{"city":"Manaus","city_ibge_code":"1302603","confirmed":205,"confirmed_per_100k_inhabitants":9.39177,"date":"2020-04-02","death_rate":0.0098,"deaths":2,"estimated_population_2019":2182763,"is_last":false,"order_for_place":17,"place_type":"city","state":"AM"},{"city":"Manaus","city_ibge_code":"1302603","confirmed":179,"confirmed_per_100k_inhabitants":8.20062,"date":"2020-04-01","death_rate":0.0112,"deaths":2,"estimated_population_2019":2182763,"is_last":false,"order_for_place":16,"place_type":"city","state":"AM"},{"city":"Manaus","city_ibge_code":"1302603","confirmed":159,"confirmed_per_100k_inhabitants":7.28435,"date":"2020-03-31","death_rate":0.0126,"deaths":2,"estimated_population_2019":2182763,"is_last":false,"order_for_place":15,"place_type":"city","state":"AM"},{"city":"Manaus","city_ibge_code":"1302603","confirmed":140,"confirmed_per_100k_inhabitants":6.41389,"date":"2020-03-30","death_rate":0.0071,"deaths":1,"estimated_population_2019":2182763,"is_last":false,"order_for_place":14,"place_type":"city","state":"AM"},{"city":"Manaus","city_ibge_code":"1302603","confirmed":131,"confirmed_per_100k_inhabitants":6.00157,"date":"2020-03-29","death_rate":0.0,"deaths":0,"estimated_population_2019":2182763,"is_last":false,"order_for_place":13,"place_type":"city","state":"AM"},{"city":"Manaus","city_ibge_code":"1302603","confirmed":105,"confirmed_per_100k_inhabitants":4.81042,"date":"2020-03-28","death_rate":0.0,"deaths":0,"estimated_population_2019":2182763,"is_last":false,"order_for_place":12,"place_type":"city","state":"AM"},{"city":"Manaus","city_ibge_code":"1302603","confirmed":75,"confirmed_per_100k_inhabitants":3.43601,"date":"2020-03-27","death_rate":0.0,"deaths":0,"estimated_population_2019":2182763,"is_last":false,"order_for_place":11,"place_type":"city","state":"AM"},{"city":"Manaus","city_ibge_code":"1302603","confirmed":63,"confirmed_per_100k_inhabitants":2.88625,"date":"2020-03-26","death_rate":0.0,"deaths":0,"estimated_population_2019":2182763,"is_last":false,"order_for_place":10,"place_type":"city","state":"AM"},{"city":"Manaus","city_ibge_code":"1302603","confirmed":52,"confirmed_per_100k_inhabitants":2.3823,"date":"2020-03-25","death_rate":0.0,"deaths":0,"estimated_population_2019":2182763,"is_last":false,"order_for_place":9,"place_type":"city","state":"AM"},{"city":"Manaus","city_ibge_code":"1302603","confirmed":45,"confirmed_per_100k_inhabitants":2.06161,"date":"2020-03-24","death_rate":0.0,"deaths":0,"estimated_population_2019":2182763,"is_last":false,"order_for_place":8,"place_type":"city","state":"AM"},{"city":"Manaus","city_ibge_code":"1302603","confirmed":31,"confirmed_per_100k_inhabitants":1.42022,"date":"2020-03-23","death_rate":0.0,"deaths":0,"estimated_population_2019":2182763,"is_last":false,"order_for_place":7,"place_type":"city","state":"AM"},{"city":"Manaus","city_ibge_code":"1302603","confirmed":25,"confirmed_per_100k_inhabitants":1.14534,"date":"2020-03-22","death_rate":0.0,"deaths":0,"estimated_population_2019":2182763,"is_last":false,"order_for_place":6,"place_type":"city","state":"AM"},{"city":"Manaus","city_ibge_code":"1302603","confirmed":11,"confirmed_per_100k_inhabitants":0.50395,"date":"2020-03-21","death_rate":0.0,"deaths":0,"estimated_population_2019":2182763,"is_last":false,"order_for_place":5,"place_type":"city","state":"AM"},{"city":"Manaus","city_ibge_code":"1302603","confirmed":7,"confirmed_per_100k_inhabitants":0.32069,"date":"2020-03-20","death_rate":0.0,"deaths":0,"estimated_population_2019":2182763,"is_last":false,"order_for_place":4,"place_type":"city","state":"AM"},{"city":"Manaus","city_ibge_code":"1302603","confirmed":3,"confirmed_per_100k_inhabitants":0.13744,"date":"2020-03-19","death_rate":0.0,"deaths":0,"estimated_population_2019":2182763,"is_last":false,"order_for_place":3,"place_type":"city","state":"AM"},{"city":"Manaus","city_ibge_code":"1302603","confirmed":2,"confirmed_per_100k_inhabitants":0.09163,"date":"2020-03-18","death_rate":0.0,"deaths":0,"estimated_population_2019":2182763,"is_last":false,"order_for_place":2,"place_type":"city","state":"AM"},{"city":"Manaus","city_ibge_code":"1302603","confirmed":2,"confirmed_per_100k_inhabitants":0.09163,"date":"2020-03-13","death_rate":0.0,"deaths":0,"estimated_population_2019":2182763,"is_last":false,"order_for_place":1,"place_type":"city","state":"AM"}]}